zcommand/__init__.py
zcommand/zcommand.py
zcommand-0.0.9.dist-info/DESCRIPTION.rst
zcommand-0.0.9.dist-info/METADATA
zcommand-0.0.9.dist-info/RECORD
zcommand-0.0.9.dist-info/WHEEL
zcommand-0.0.9.dist-info/metadata.json
zcommand-0.0.9.dist-info/top_level.txt
