Metadata-Version: 2.0
Name: zcommand
Version: 0.0.9
Summary: command line args
Home-page: https://github.com/izhengzhixian/zcommand
Author: UNKNOWN
Author-email: UNKNOWN
License: UNKNOWN
Platform: UNKNOWN
